LICENSE
README.md
setup.py
pystache_cli/__init__.py
pystache_cli/pystache_cli.py
pystache_cli.egg-info/PKG-INFO
pystache_cli.egg-info/SOURCES.txt
pystache_cli.egg-info/dependency_links.txt
pystache_cli.egg-info/entry_points.txt
pystache_cli.egg-info/requires.txt
pystache_cli.egg-info/top_level.txt
tests/__init__.py
tests/test.py
tests/data/context.json
tests/data/template.json