Metadata-Version: 2.1
Name: pystache-cli
Version: 0.3.4
Summary: Extended command line client for pystache
Home-page: https://github.com/wingechr/pystache-cli
Author: Christian Winger
Author-email: c@wingechr.de
License: Public Domain
Download-URL: https://github.com/wingechr/pystache-cli
Project-URL: Bug Tracker, https://github.com/wingechr/pystache-cli
Keywords: cli,pystache,template
Platform: any
Classifier: Programming Language :: Python :: 3
Classifier: License :: CC0 1.0 Universal (CC0 1.0) Public Domain Dedication
Classifier: Operating System :: OS Independent
License-File: LICENSE
